G31_KID_pipeline/G31_KID_pipeline.py
G31_KID_pipeline/__init__.py
G31_KID_pipeline-1.0.0.dist-info/METADATA
G31_KID_pipeline-1.0.0.dist-info/WHEEL
G31_KID_pipeline-1.0.0.dist-info/top_level.txt
G31_KID_pipeline-1.0.0.dist-info/RECORD
