Metadata-Version: 2.1
Name: G31-KID-pipeline
Version: 1.0.0
Summary: A pipeline for KID data analysis
Author-email: Federico Cacciotti <federico.cacciotti@roma1.infn.it>
Project-URL: Homepage, https://github.com/federico-cacciotti/KID_pipeline
Classifier: Programming Language :: Python :: 3
Classifier: License :: OSI Approved :: MIT License
Classifier: Operating System :: OS Independent
Requires-Python: >=3.7
